pycm/__init__.py
pycm/__main__.py
pycm/basic_test.py
pycm/ci.py
pycm/class_funcs.py
pycm/cm.py
pycm/compare.py
pycm/curve.py
pycm/distance.py
pycm/errors.py
pycm/generate_random_data.py
pycm/handlers.py
pycm/interpret.py
pycm/multilabel_cm.py
pycm/output.py
pycm/overall_funcs.py
pycm/params.py
pycm/profile.py
pycm/utils.py
pycm-4.5.dist-info/licenses/AUTHORS.md
pycm-4.5.dist-info/licenses/LICENSE
pycm-4.5.dist-info/METADATA
pycm-4.5.dist-info/WHEEL
pycm-4.5.dist-info/top_level.txt
pycm-4.5.dist-info/RECORD
